wordvecspace/__init__.py
wordvecspace/annoy.py
wordvecspace/base.py
wordvecspace/command.py
wordvecspace/convert.py
wordvecspace/cuda.py
wordvecspace/disk.py
wordvecspace/exception.py
wordvecspace/fileformat.py
wordvecspace/mem.py
wordvecspace/server.py
wordvecspace/wvspace.py
wordvecspace-0.5.6.dist-info/LICENSE
wordvecspace-0.5.6.dist-info/METADATA
wordvecspace-0.5.6.dist-info/WHEEL
wordvecspace-0.5.6.dist-info/entry_points.txt
wordvecspace-0.5.6.dist-info/top_level.txt
wordvecspace-0.5.6.dist-info/RECORD
