Metadata-Version: 2.1
Name: wordvecspace
Version: 0.5.6
Summary: A high performance pure python module that helps in loading and performing operations on word vector spaces created using Google's Word2vec tool. It also supports converting word vector space data (vectors and vocabulary) from Google Word2Vec format to WordVecSpace format.
Home-page: https://github.com/deep-compute/wordvecspace
Author: Deep Compute, LLC
Author-email: contact@deepcompute.com
License: MIT License
Download-URL: https://github.com/deep-compute/wordvecspace/tarball/0.5.6
Keywords: wordvecspace
Platform: UNKNOWN
Classifier: Programming Language :: Python :: 3.5
Classifier: Environment :: Console
Classifier: Intended Audience :: Developers
Classifier: License :: OSI Approved :: MIT License
Requires-Python: >3.5.1
Requires-Dist: annoy (==1.11.4)
Requires-Dist: scipy (==1.0.0)
Requires-Dist: diskarray (==0.1.8)
Requires-Dist: diskdict (==0.2.2)
Requires-Dist: deeputil (==0.2.5)
Requires-Dist: bottleneck (==1.2.1)
Requires-Dist: pandas (==0.23.4)
Provides-Extra: cuda
Requires-Dist: pycuda (==2018.1.1) ; extra == 'cuda'
Requires-Dist: scikit-cuda (==0.5.1) ; extra == 'cuda'
Provides-Extra: service
Requires-Dist: kwikapi[tornado] (==0.4.5) ; extra == 'service'
